Workbook

Sheet Assumptions
A1: CRAMAPPLE — MODEL ASSUMPTIONS
B2: Aug-Dec 2026 | C2: Jan-Mar 2027 | D2: Apr-May 2027 | E2: Jun-Dec 2027 | F2: FY 2027 | G2: Notes
A3: PRODUCT & PRICING
A4: Base price per subject ($) | B4: 39.99 | C4: 39.99 | D4: 39.99 | E4: 39.99 | F4: 39.99 | G4: Single subject, one-time purchase
A5: Refund rate (%) | B5: 0.05 | C5: 0.05 | D5: 0.05 | E5: 0.05 | F5: 0.05 | G5: Estimate — adjust after launch data
A6: Avg subjects per customer | B6: 1 | C6: 1 | D6: 1 | E6: 1 | F6: 1 | G6: Single-SKU launch; expand model later
A8: VARIABLE COST — AI INFERENCE
A9: Avg sessions per user | B9: 6 | C9: 6 | D9: 6 | E9: 6 | F9: 6 | G9: Placeholder; light=3, heavy=10 — update with August data
A10: Avg exchanges per session | B10: 10 | C10: 10 | D10: 10 | E10: 10 | F10: 10 | G10: Mix of MC, instruction, FRQ turns
A11: Avg input tokens per exchange | B11: 2500 | C11: 2500 | D11: 2500 | E11: 2500 | F11: 2500 | G11: Includes system prompt / canonical context loaded each session
A12: Avg output tokens per exchange | B12: 500 | C12: 500 | D12: 500 | E12: 500 | F12: 500 | G12: FRQ feedback ~600 tokens; MC ~150
A13: Input token rate ($ per 1M) | B13: 3 | C13: 3 | D13: 3 | E13: 3 | F13: 3 | G13: Claude Sonnet approx — update when model is locked
A14: Output token rate ($ per 1M) | B14: 15 | C14: 15 | D14: 15 | E14: 15 | F14: 15 | G14: Claude Sonnet approx — update when model is locked
A15: → Inference cost per user ($) | B15: =B8*B9*((B10*B12/1000000)+(B11*B13/1000000)) -> 0 | C15: =C8*C9*((C10*C12/1000000)+(C11*C13/1000000)) -> 0 | D15: =D8*D9*((D10*D12/1000000)+(D11*D13/1000000)) -> 0 | E15: =E8*E9*((E10*E12/1000000)+(E11*E13/1000000)) -> 0 | F15: =F8*F9*((F10*F12/1000000)+(F11*F13/1000000)) -> 0 | G15: sessions × exchanges × ((input_tokens×input_rate) + (output_tokens×output_rate))
A17: ACQUISITION — FIXED SPEND CHANNELS (monthly budget $)
A18: Influencer / creator spend ($/mo) | B18: 0 | C18: 250 | D18: 500 | E18: 500 | F18: 500 | G18: Monthly budget — you adjust per channel
A19: Paid social / ads spend ($/mo) | B19: 0 | C19: 250 | D19: 500 | E19: 500 | F19: 500 | G19: Instagram, TikTok — optimize based on results
A20: Conversion rate — paid social (%) | B20: 0.01 | C20: 0.02 | D20: 0.03 | E20: 0.03 | F20: 0.03 | G20: Industry 2-4%; Aug=learning phase, use 1%
A21: Avg CPC ($ per click) | B21: 1.5 | C21: 1.5 | D21: 1.5 | E21: 1.5 | F21: 1.5 | G21: Replace with actuals from first campaign
A23: ACQUISITION — REFERRAL (performance; no budget)
A24: Referral fee (% of sale) | B24: 0.2 | C24: 0.2 | D24: 0.2 | E24: 0.2 | F24: 0.2 | G24: 20% = $8 per $39.99 sale; success-only, no cap
A25: Referral % of new users (est.) | B25: 0 | C25: 0.05 | D25: 0.1 | E25: 0.15 | F25: 0.12 | G25: Grows as tutor channel matures; zero until program launches
A27: ACQUISITION — ORGANIC / DIRECT
A28: Organic new users per period | B28: 10 | C28: 25 | D28: 75 | E28: 50 | F28: 150 | G28: Personal network, word of mouth, earned media
A30: OTHER VARIABLE COSTS
A31: Payment processing — % of revenue | B31: 0.029 | C31: 0.029 | D31: 0.029 | E31: 0.029 | F31: 0.029 | G31: Stripe 2.9%
A32: Payment processing — per transaction ($) | B32: 0.3 | C32: 0.3 | D32: 0.3 | E32: 0.3 | F32: 0.3 | G32: Stripe $0.30 flat fee
A33: Support cost per user ($) | B33: 1 | C33: 1 | D33: 1 | E33: 1 | F33: 1 | G33: Estimate — update as support volume becomes visible
A36: COLOR LEGEND
A37: Blue text = input (you change this)
A38: Black text = calculated formula
A39: Green text = linked from another sheet
A40: Yellow background = key assumption — review before presenting

Sheet P&L Model
A1: CRAMAPPLE — UNIT ECONOMICS & P&L
B2: Aug-Dec 2026 | C2: Jan-Mar 2027 | D2: Apr-May 2027 | E2: Jun-Dec 2027 | F2: FY 2027 | G2: Notes
A3: USER ACQUISITION
A4: Paid social users acquired | B4: =ROUND((Assumptions!B19*5/Assumptions!B21)*Assumptions!B20,0) -> 0 | C4: =ROUND((Assumptions!C19*3/Assumptions!C21)*Assumptions!C20,0) -> 10 | D4: =ROUND((Assumptions!D19*2/Assumptions!D21)*Assumptions!D20,0) -> 20 | E4: =ROUND((Assumptions!E19*7/Assumptions!E21)*Assumptions!E20,0) -> 70 | F4: =ROUND((Assumptions!F19*12/Assumptions!F21)*Assumptions!F20,0) -> 120 | G4: (budget / CPC) x conv rate x months in period
A5: Organic users acquired | B5: =Assumptions!B28 -> 10 | C5: =Assumptions!C28 -> 25 | D5: =Assumptions!D28 -> 75 | E5: =Assumptions!E28 -> 50 | F5: =Assumptions!F28 -> 150 | G5: From Assumptions organic row
A6: Referral users acquired | B6: =ROUND((B4+B5)*Assumptions!B25/(1-IF(Assumptions!B25>=0.999,0.999,Assumptions!B25)),0) -> 0 | C6: =ROUND((C4+C5)*Assumptions!C25/(1-IF(Assumptions!C25>=0.999,0.999,Assumptions!C25)),0) -> 2 | D6: =ROUND((D4+D5)*Assumptions!D25/(1-IF(Assumptions!D25>=0.999,0.999,Assumptions!D25)),0) -> 11 | E6: =ROUND((E4+E5)*Assumptions!E25/(1-IF(Assumptions!E25>=0.999,0.999,Assumptions!E25)),0) -> 21 | F6: =ROUND((F4+F5)*Assumptions!F25/(1-IF(Assumptions!F25>=0.999,0.999,Assumptions!F25)),0) -> 37 | G6: (paid + organic) x ref share / (1 - ref share)
A7: Total new users | B7: =B4+B5+B6 -> 10 | C7: =C4+C5+C6 -> 37 | D7: =D4+D5+D6 -> 106 | E7: =E4+E5+E6 -> 141 | F7: =F4+F5+F6 -> 307 | G7: Sum of all acquisition channels
A9: REVENUE
A10: Gross revenue | B10: =B7*Assumptions!B4*Assumptions!B6 -> 399.9 | C10: =C7*Assumptions!C4*Assumptions!C6 -> 1479.63 | D10: =D7*Assumptions!D4*Assumptions!D6 -> 4238.94 | E10: =E7*Assumptions!E4*Assumptions!E6 -> 5638.59 | F10: =F7*Assumptions!F4*Assumptions!F6 -> 12276.93 | G10: Users × price × avg subjects
A11: Less: refunds | B11: =-B10*Assumptions!B5 -> -19.995 | C11: =-C10*Assumptions!C5 -> -73.9815 | D11: =-D10*Assumptions!D5 -> -211.947 | E11: =-E10*Assumptions!E5 -> -281.9295 | F11: =-F10*Assumptions!F5 -> -613.8465 | G11: Gross rev × refund rate
A12: Net revenue | B12: =B10+B11 -> 379.905 | C12: =C10+C11 -> 1405.6485 | D12: =D10+D11 -> 4026.993 | E12: =E10+E11 -> 5356.6605 | F12: =F10+F11 -> 11663.084 | G12: Gross less refunds
A14: VARIABLE COSTS
A15: AI inference cost | B15: =-B7*Assumptions!B15 -> 0 | C15: =-C7*Assumptions!C15 -> 0 | D15: =-D7*Assumptions!D15 -> 0 | E15: =-E7*Assumptions!E15 -> 0 | F15: =-F7*Assumptions!F15 -> 0 | G15: Users × inference cost/user
A16: Payment processing — % fee | B16: =-B12*Assumptions!B31 -> -11.017245 | C16: =-C12*Assumptions!C31 -> -40.763807 | D16: =-D12*Assumptions!D31 -> -116.7828 | E16: =-E12*Assumptions!E31 -> -155.34315 | F16: =-F12*Assumptions!F31 -> -338.22942 | G16: Stripe 2.9% of net revenue
A17: Payment processing — per-txn | B17: =-B7*Assumptions!B32 -> -3 | C17: =-C7*Assumptions!C32 -> -11.1 | D17: =-D7*Assumptions!D32 -> -31.8 | E17: =-E7*Assumptions!E32 -> -42.3 | F17: =-F7*Assumptions!F32 -> -92.1 | G17: $0.30 × total users
A18: Referral fees paid | B18: =-B6*Assumptions!B4*Assumptions!B24 -> 0 | C18: =-C6*Assumptions!C4*Assumptions!C24 -> -15.996 | D18: =-D6*Assumptions!D4*Assumptions!D24 -> -87.978 | E18: =-E6*Assumptions!E4*Assumptions!E24 -> -167.958 | F18: =-F6*Assumptions!F4*Assumptions!F24 -> -295.926 | G18: Referral users × price × 20%
A19: Paid social spend | B19: =-Assumptions!B19*5 -> 0 | C19: =-Assumptions!C19*3 -> -750 | D19: =-Assumptions!D19*2 -> -1000 | E19: =-Assumptions!E19*7 -> -3500 | F19: =-Assumptions!F19*12 -> -6000 | G19: Monthly ad budget × months in period
A20: Influencer / creator spend | B20: =-Assumptions!B18*5 -> 0 | C20: =-Assumptions!C18*3 -> -750 | D20: =-Assumptions!D18*2 -> -1000 | E20: =-Assumptions!E18*7 -> -3500 | F20: =-Assumptions!F18*12 -> -6000 | G20: Monthly influencer budget × months in period
A21: Support costs | B21: =-B7*Assumptions!B33 -> -10 | C21: =-C7*Assumptions!C33 -> -37 | D21: =-D7*Assumptions!D33 -> -106 | E21: =-E7*Assumptions!E33 -> -141 | F21: =-F7*Assumptions!F33 -> -307 | G21: $1/user placeholder
A22: Total variable costs | B22: =SUM(B15:B21) -> -24.017245 | C22: =SUM(C15:C21) -> -1604.8598 | D22: =SUM(D15:D21) -> -2342.5608 | E22: =SUM(E15:E21) -> -7506.6012 | F22: =SUM(F15:F21) -> -13033.255 | G22: Sum of all variable cost lines
A24: CONTRIBUTION MARGIN
A25: Contribution margin ($) | B25: =IF(B12=0,0,B24/B12) -> 0 | C25: =IF(C12=0,0,C24/C12) -> 0 | D25: =IF(D12=0,0,D24/D12) -> 0 | E25: =IF(E12=0,0,E24/E12) -> 0 | F25: =IF(F12=0,0,F24/F12) -> 0 | G25: Net revenue + total variable costs (costs are negative)
A26: Contribution margin (%) | B26: =IF(B12=0,0,B25/B12) -> 0 | C26: =IF(C12=0,0,C25/C12) -> 0 | D26: =IF(D12=0,0,D25/D12) -> 0 | E26: =IF(E12=0,0,E25/E12) -> 0 | F26: =IF(F12=0,0,F25/F12) -> 0 | G26: CM ÷ net revenue
A28: PER-USER METRICS — KEY INDICATORS
A29: Revenue per user ($) | B29: =IF(B7=0,0,B22/B7) -> -2.4017245 | C29: =IF(C7=0,0,C22/C7) -> -43.374589 | D29: =IF(D7=0,0,D22/D7) -> -22.09963 | E29: =IF(E7=0,0,E22/E7) -> -53.238306 | F29: =IF(F7=0,0,F22/F7) -> -42.453601 | G29: Net revenue ÷ total users
A30: Variable cost per user ($) | B30: =IF(B7=0,0,B24/B7) -> 0 | C30: =IF(C7=0,0,C24/C7) -> 0 | D30: =IF(D7=0,0,D24/D7) -> 0 | E30: =IF(E7=0,0,E24/E7) -> 0 | F30: =IF(F7=0,0,F24/F7) -> 0 | G30: Total variable cost ÷ users (will be negative)
A31: Contribution per user ($) | B31: =IF(B7=0,0,B25/B7) -> 0 | C31: =IF(C7=0,0,C25/C7) -> 0 | D31: =IF(D7=0,0,D25/D7) -> 0 | E31: =IF(E7=0,0,E25/E7) -> 0 | F31: =IF(F7=0,0,F25/F7) -> 0 | G31: CM ÷ users — margin per sale after all variable costs
A33: CUSTOMER ACQUISITION COST (CAC)
A34: Total paid acquisition spend ($) | B34: =B4 -> 0 | C34: =C4 -> 10 | D34: =D4 -> 20 | E34: =E4 -> 70 | F34: =F4 -> 120 | G34: (Influencer + paid social) × months in period
A35: Paid social users only | B35: =IF(B34=0,0,B33/B34) -> 0 | C35: =IF(C34=0,0,C33/C34) -> 0 | D35: =IF(D34=0,0,D33/D34) -> 0 | E35: =IF(E34=0,0,E33/E34) -> 0 | F35: =IF(F34=0,0,F33/F34) -> 0 | G35: Paid channel users from acquisition section
A36: CAC — paid channels only ($) | B36: =IF(B7=0,0,B33/B7) -> 0 | C36: =IF(C7=0,0,C33/C7) -> 0 | D36: =IF(D7=0,0,D33/D7) -> 0 | E36: =IF(E7=0,0,E33/E7) -> 0 | F36: =IF(F7=0,0,F33/F7) -> 0 | G36: Paid spend ÷ paid users acquired
A37: CAC — blended all channels ($) | B37: =IF(B7=0,0,B34/B7) -> 0 | C37: =IF(C7=0,0,C34/C7) -> 0.27027027 | D37: =IF(D7=0,0,D34/D7) -> 0.18867925 | E37: =IF(E7=0,0,E34/E7) -> 0.4964539 | F37: =IF(F7=0,0,F34/F7) -> 0.39087948 | G37: Paid spend ÷ ALL users (organic and referral dilute CAC)

Sheet Scenarios
A1: SPRING 2027 SCENARIO STRESS TEST (Apr-May 2027 — 2-month primary window)
B2: Bear | C2: Base | D2: Bull | E2: Notes
A3: INPUTS
A4: Total users (2-month period) | B4: 50 | C4: 200 | D4: 500 | E4: Bear=soft launch only; Bull=word of mouth working
A5: Price ($) | B5: 39.99 | C5: 39.99 | D5: 39.99 | E5: Held constant; test discounts separately
A6: Inference cost per user ($) | B6: 3.5 | C6: 2.5 | D6: 1.8 | E6: Bear=heavy FRQ use; Bull=efficient session mix
A7: Referral % of users | B7: 0.05 | C7: 0.1 | D7: 0.2 | E7: Grows as tutor referral channel matures
A8: Total paid social spend ($) | B8: 1000 | C8: 1000 | D8: 1000 | E8: Fixed 2-month budget across scenarios
A9: Refund rate (%) | B9: 0.08 | C9: 0.05 | D9: 0.03 | E9: Bear reflects grading quality risk
A11: OUTPUTS
A12: Gross revenue | B12: =B4*B5 -> 1999.5 | C12: =C4*C5 -> 7998 | D12: =D4*D5 -> 19995 | E12: Users × price
A13: Net revenue (after refunds) | B13: =B12*(1-B9) -> 1839.54 | C13: =C12*(1-C9) -> 7598.1 | D13: =D12*(1-D9) -> 19395.15
A14: AI inference cost | B14: =-B4*B6 -> -175 | C14: =-C4*C6 -> -500 | D14: =-D4*D6 -> -900
A16: Referral fees | B16: =-B4*B7*B5*0.2 -> -19.995 | C16: =-C4*C7*C5*0.2 -> -159.96 | D16: =-D4*D7*D5*0.2 -> -799.8 | E16: Referral users × price × 20%
A17: Payment processing | B17: =-(B12*0.029+B4*0.3) -> -72.9855 | C17: =-(C12*0.029+C4*0.3) -> -291.942 | D17: =-(D12*0.029+D4*0.3) -> -729.855 | E17: 2.9% + $0.30/txn
A18: Paid social spend | B18: =-B8 -> -1000 | C18: =-C8 -> -1000 | D18: =-D8 -> -1000 | E18: Fixed budget input
A19: Support costs | B19: =-B4*1 -> -50 | C19: =-C4*1 -> -200 | D19: =-D4*1 -> -500 | E19: $1/user
A20: Contribution margin ($) | B20: =B13+SUM(B14:B19) -> 521.5595 | C20: =C13+SUM(C14:C19) -> 5446.198 | D20: =D13+SUM(D14:D19) -> 15465.495 | E20: Net rev + all variable costs
A21: CM per user ($) | B21: =IF(B4=0,0,B20/B4) -> 10.43119 | C21: =IF(C4=0,0,C20/C4) -> 27.23099 | D21: =IF(D4=0,0,D20/D4) -> 30.93099
A22: Blended CAC ($) | B22: =IF(B4=0,0,B8/B4) -> 20 | C22: =IF(C4=0,0,C8/C4) -> 5 | D22: =IF(D4=0,0,D8/D4) -> 2 | E22: Paid spend ÷ total users
A23: Revenue per user ($) | B23: =IF(B4=0,0,B13/B4) -> 36.7908 | C23: =IF(C4=0,0,C13/C4) -> 37.9905 | D23: =IF(D4=0,0,D13/D4) -> 38.7903 | E23: Net revenue ÷ total users

Sheet Inference Sensitivity
A1: AI INFERENCE COST SENSITIVITY — Cost per User ($) | Input rate fixed at $3.00/1M
A2: Sessions per user → | B2: 3 | C2: 5 | D2: 6 | E2: 8 | F2: 10 | G2: Blue cell = base case (6 sessions, $15 output rate)
A3: Output rate $10.00/1M | B3: 0.375 | C3: 0.625 | D3: 0.75 | E3: 1 | F3: 1.25 | G3: sessions x 10 exchanges x token costs
A4: Output rate $12.00/1M | B4: 0.405 | C4: 0.675 | D4: 0.81 | E4: 1.08 | F4: 1.35 | G4: sessions x 10 exchanges x token costs
A5: Output rate $15.00/1M | B5: 0.45 | C5: 0.75 | D5: 0.9 | E5: 1.2 | F5: 1.5 | G5: sessions x 10 exchanges x token costs
A6: Output rate $18.00/1M | B6: 0.495 | C6: 0.825 | D6: 0.99 | E6: 1.32 | F6: 1.65 | G6: sessions x 10 exchanges x token costs
A7: Output rate $22.00/1M | B7: 0.555 | C7: 0.925 | D7: 1.11 | E7: 1.48 | F7: 1.85 | G7: sessions x 10 exchanges x token costs
A9: Assumptions: 10 exchanges/session | 2,500 input tokens/exchange | 500 output tokens/exchange | input rate $3.00/1M
